README.md
setup.cfg
setup.py
bart/__init__.py
bart/version.py
bart/common/Analyzer.py
bart/common/Utils.py
bart/common/__init__.py
bart/common/signal.py
bart/sched/SchedAssert.py
bart/sched/SchedMatrix.py
bart/sched/SchedMultiAssert.py
bart/sched/__init__.py
bart/sched/functions.py
bart/sched/pelt.py
bart/thermal/ThermalAssert.py
bart/thermal/__init__.py
bart_py.egg-info/PKG-INFO
bart_py.egg-info/SOURCES.txt
bart_py.egg-info/dependency_links.txt
bart_py.egg-info/requires.txt
bart_py.egg-info/top_level.txt