Metadata-Version: 1.1
Name: bart-py
Version: 2.0.0
Summary: Behavioural Analysis and Regression Toolkit
Home-page: http://arm-software.github.io/bart
Author: ARM-BART
Author-email: bart@arm.com
License: Apache v2
Platform: UNKNOWN
Classifier: Development Status :: 5 - Production/Stable
Classifier: Environment :: Web Environment
Classifier: Environment :: Console
Classifier: License :: OSI Approved :: Apache Software License
Classifier: Operating System :: POSIX :: Linux
Classifier: Programming Language :: Python :: 2.7
Classifier: Topic :: System :: Operating System Kernels :: Linux
Classifier: Topic :: Scientific/Engineering :: Visualization
